llama_index/readers/hive/__init__.py
llama_index/readers/hive/base.py
llama_index_readers_hive-0.3.1.dist-info/METADATA
llama_index_readers_hive-0.3.1.dist-info/WHEEL
llama_index_readers_hive-0.3.1.dist-info/licenses/LICENSE
llama_index_readers_hive-0.3.1.dist-info/RECORD
