Metadata-Version: 2.4
Name: llama-index-readers-hive
Version: 0.3.1
Summary: llama-index readers hive integration
Author-email: Your Name <you@example.com>
Maintainer: kasen
License-Expression: MIT
License-File: LICENSE
Keywords: HDFS,Hadoop,Hive
Requires-Python: <4.0,>=3.9
Requires-Dist: deprecated<2,>=1.2.18
Requires-Dist: llama-index-core<0.13,>=0.12.0
Requires-Dist: pyhive<0.8,>=0.7.0
Requires-Dist: sqlglot<27,>=26.25.3
Requires-Dist: thrift-sasl<0.5,>=0.4.3
